pybuilder_pyproject_toml/__init__.py
pybuilder_pyproject_toml-0.0.18.dist-info/METADATA
pybuilder_pyproject_toml-0.0.18.dist-info/WHEEL
pybuilder_pyproject_toml-0.0.18.dist-info/namespace_packages.txt
pybuilder_pyproject_toml-0.0.18.dist-info/top_level.txt
pybuilder_pyproject_toml-0.0.18.dist-info/zip-safe
pybuilder_pyproject_toml-0.0.18.dist-info/RECORD
